llama_index/packs/gmail_openai_agent/__init__.py
llama_index/packs/gmail_openai_agent/base.py
llama_index_packs_gmail_openai_agent-0.4.1.dist-info/METADATA
llama_index_packs_gmail_openai_agent-0.4.1.dist-info/WHEEL
llama_index_packs_gmail_openai_agent-0.4.1.dist-info/licenses/LICENSE
llama_index_packs_gmail_openai_agent-0.4.1.dist-info/RECORD
