Metadata-Version: 2.4
Name: llama-index-packs-gmail-openai-agent
Version: 0.4.1
Summary: llama-index packs gmail_openai_agent integration
Author-email: Your Name <you@example.com>
Maintainer: logan-markewich
License-Expression: MIT
License-File: LICENSE
Keywords: math,research,science
Requires-Python: <4.0,>=3.9
Requires-Dist: llama-index-core<0.15,>=0.13.0
Requires-Dist: llama-index-tools-google<0.7,>=0.6.0
